aivpp.py
aivpp-0.1.14.dist-info/licenses/LICENSE
aivpp-0.1.14.dist-info/METADATA
aivpp-0.1.14.dist-info/WHEEL
aivpp-0.1.14.dist-info/entry_points.txt
aivpp-0.1.14.dist-info/top_level.txt
aivpp-0.1.14.dist-info/RECORD
