Metadata-Version: 2.4
Name: aivpp
Version: 0.1.14
Summary: AIVPP MCP Server
Requires-Python: >=3.12
License-File: LICENSE
Requires-Dist: httpx>=0.28.1
Requires-Dist: mcp[cli]>=1.11.0
Requires-Dist: requests>=2.31.0
Requires-Dist: pandas>=2.3.1
Requires-Dist: alibabacloud_brain_industrial20200920>=2.1.0
Requires-Dist: alibabacloud_sts20150401>=1.1.6
Requires-Dist: pydantic>=2.11.7
Dynamic: license-file
